machotools/__init__.py
machotools/__main__.py
machotools/__version.py
machotools/common.py
machotools/dependency.py
machotools/detect.py
machotools/errors.py
machotools/macho_rewriter.py
machotools/misc.py
machotools/rpath.py
machotools/utils.py
machotools/tests/__init__.py
machotools/tests/common.py
machotools/tests/test_dependency.py
machotools/tests/test_detect.py
machotools/tests/test_install_name.py
machotools/tests/test_macho_rewriter.py
machotools/tests/test_rpath.py
machotools-0.2.0.dist-info/DESCRIPTION.rst
machotools-0.2.0.dist-info/METADATA
machotools-0.2.0.dist-info/RECORD
machotools-0.2.0.dist-info/WHEEL
machotools-0.2.0.dist-info/metadata.json
machotools-0.2.0.dist-info/top_level.txt
