Metadata-Version: 2.0
Name: machotools
Version: 0.2.0
Summary: UNKNOWN
Home-page: UNKNOWN
Author: David Cournapeau
Author-email: cournape@gmail.com
License: BSD
Platform: UNKNOWN
Classifier: Programming Language :: Python :: 2.7
Classifier: Programming Language :: Python :: 3.5
Classifier: Programming Language :: Python :: 3.6
Requires-Dist: macholib
